tajik_text_segmentation/__init__.py
tajik_text_segmentation/annotated.py
tajik_text_segmentation/boundary_resolver.py
tajik_text_segmentation/config.json
tajik_text_segmentation/heuristic_model.py
tajik_text_segmentation/text_segmenter.py
tajik_text_segmentation/tokenizer.py
tajik_text_segmentation/__pycache__/__init__.cpython-39.pyc
tajik_text_segmentation/__pycache__/annotated.cpython-39.pyc
tajik_text_segmentation/__pycache__/boundary_resolver.cpython-39.pyc
tajik_text_segmentation/__pycache__/heuristic_model.cpython-39.pyc
tajik_text_segmentation/__pycache__/text_segmenter.cpython-39.pyc
tajik_text_segmentation/__pycache__/tokenizer.cpython-39.pyc
tajik_text_segmentation/checkpoints/checkpoint.pt
tajik_text_segmentation/nn_model/__init__.py
tajik_text_segmentation/nn_model/model.py
tajik_text_segmentation/nn_model/vocab.py
tajik_text_segmentation/nn_model/__pycache__/__init__.cpython-39.pyc
tajik_text_segmentation/nn_model/__pycache__/model.cpython-39.pyc
tajik_text_segmentation/nn_model/__pycache__/vocab.cpython-39.pyc
tests/__init__.py
tests/test_dataset.py
tests/test_evaluate.py
tests/test_heuristic_model.py
tests/test_tokenizer.py
training/__init__.py
training/dummy_model.py
training/evaluate.py
training/utils.py
tajik_text_segmentation-0.1.7.dist-info/METADATA
tajik_text_segmentation-0.1.7.dist-info/WHEEL
tajik_text_segmentation-0.1.7.dist-info/top_level.txt
tajik_text_segmentation-0.1.7.dist-info/RECORD
