Metadata-Version: 2.1
Name: tajik-text-segmentation
Version: 0.1.7
Summary: A package for Tajik text segmentation using a heuristic algorithm and neural network.
Home-page: https://github.com/sobir-git/tajik-text-segmentation
Author: Sobir Bobiev
Author-email: sobir.bobiev@gmail.com
Classifier: Development Status :: 3 - Alpha
Classifier: Intended Audience :: Developers
Classifier: License :: OSI Approved :: MIT License
Classifier: Programming Language :: Python :: 3
Classifier: Programming Language :: Python :: 3.6
Classifier: Programming Language :: Python :: 3.7
Classifier: Programming Language :: Python :: 3.8
Classifier: Programming Language :: Python :: 3.9
Requires-Python: >=3.6
Requires-Dist: torch
Requires-Dist: numpy
Requires-Dist: python-dotenv
Requires-Dist: scikit-learn
